mu_pipelines_interfaces/__init__.py
mu_pipelines_interfaces/configuration_provider.py
mu_pipelines_interfaces/context.py
mu_pipelines_interfaces/destination_module_interface.py
mu_pipelines_interfaces/execute_module_interface.py
mu_pipelines_interfaces/config_types/__init__.py
mu_pipelines_interfaces/config_types/connection_properties.py
mu_pipelines_interfaces/config_types/destination_config.py
mu_pipelines_interfaces/config_types/execute_config.py
mu_pipelines_interfaces/config_types/job_config.py
mu_pipelines_interfaces/config_types/global_properties/__init__.py
mu_pipelines_interfaces/config_types/global_properties/global_properties.py
mu_pipelines_interfaces/config_types/module_mapping/__init__.py
mu_pipelines_interfaces/config_types/module_mapping/class_module_mapping.py
mu_pipelines_interfaces/config_types/module_mapping/destination_module_mapping.py
mu_pipelines_interfaces/config_types/module_mapping/execute_module_mapping.py
mu_pipelines_interfaces/config_types/module_mapping/secrets_module_mapping.py
mu_pipelines_interfaces/config_types/secrets/__init__.py
mu_pipelines_interfaces/config_types/secrets/secret_value_mapping.py
mu_pipelines_interfaces/config_types/secrets/secrets_config.py
mu_pipelines_interfaces/modules/__init__.py
mu_pipelines_interfaces/modules/destination_module_interface.py
mu_pipelines_interfaces/modules/execute_module_interface.py
mu_pipelines_interfaces/modules/injectable_module_interface.py
mu_pipelines_interfaces/modules/secrets_module_interface.py
mu_pipelines_interfaces-0.2.0a2.dist-info/entry_points.txt
mu_pipelines_interfaces-0.2.0a2.dist-info/licenses/LICENSE
mu_pipelines_interfaces-0.2.0a2.dist-info/WHEEL
mu_pipelines_interfaces-0.2.0a2.dist-info/METADATA
mu_pipelines_interfaces-0.2.0a2.dist-info/RECORD
