Metadata-Version: 2.4
Name: mu_pipelines_interfaces
Version: 0.2.0a2
Summary: mu_pipelines_interfaces
Keywords: data movement,spark,etl
Author-email: MosaicSoft <mupipelines@gmail.com>
Requires-Python: >=3.11
Classifier: Programming Language :: Python :: 3
License-File: LICENSE
Project-URL: documentation, https://mosaicsoft-data.github.io/mu-pipelines-doc/
